Workbook

Sheet Transações
A1: 📊 CALCULADORA DE IR – CRIPTOATIVOS BRASIL 2026
A2: Data | B2: Tipo | C2: Cripto | D2: Quantidade | E2: Preço Unitário (BRL) | F2: Valor Total (BRL) | G2: Taxas (BRL) | H2: Exchange/Wallet | I2: Notas
A3: 15/01/2026 | B3: Compra | C3: BTC | D3: 0.05 | E3: 580000 | F3: =D3*E3 -> 29000 | G3: 29 | H3: Binance | I3: Compra inicial BTC
A4: 20/01/2026 | B4: Venda | C4: BTC | D4: 0.02 | E4: 620000 | F4: =D4*E4 -> 12400 | G4: 12.4 | H4: Binance | I4: Venda parcial BTC – lucro
A5: 05/02/2026 | B5: Staking | C5: ETH | D5: 0.15 | E5: 17500 | F5: =D5*E5 -> 2625 | G5: 0 | H5: Lido/Ledger | I5: Rendimento staking ETH
A6: 18/02/2026 | B6: Compra | C6: SOL | D6: 10 | E6: 870 | F6: =D6*E6 -> 8700 | G6: 8.7 | H6: Coinbase | I6: Diversificação em SOL
F7: =IF(AND(D7<>"",E7<>""),D7*E7,"")
F8: =IF(AND(D8<>"",E8<>""),D8*E8,"")
F9: =IF(AND(D9<>"",E9<>""),D9*E9,"")
F10: =IF(AND(D10<>"",E10<>""),D10*E10,"")
F11: =IF(AND(D11<>"",E11<>""),D11*E11,"")
F12: =IF(AND(D12<>"",E12<>""),D12*E12,"")
F13: =IF(AND(D13<>"",E13<>""),D13*E13,"")
F14: =IF(AND(D14<>"",E14<>""),D14*E14,"")
F15: =IF(AND(D15<>"",E15<>""),D15*E15,"")
F16: =IF(AND(D16<>"",E16<>""),D16*E16,"")
F17: =IF(AND(D17<>"",E17<>""),D17*E17,"")
F18: =IF(AND(D18<>"",E18<>""),D18*E18,"")
... F1000: =IF(AND(D1000<>"",E1000<>""),D1000*E1000,"")

Sheet Apuração FIFO
A1: ⚖️ APURAÇÃO DE GANHO DE CAPITAL – MÉTODO CUSTO MÉDIO PONDERADO (RECEITA FEDERAL)
A2: Cripto | B2: Data | C2: Tipo | D2: Quantidade | E2: Preço Unitário (BRL) | F2: Custo de Aquisição (BRL) | G2: Ganho de Capital – CMP (BRL) | H2: Vendas no Mês (BRL)
A3: =IF(Transações!C3<>"",Transações!C3,"") -> BTC | B3: =IF(Transações!A3<>"",Transações!A3,"") -> 15/01/2026 | C3: =IF(Transações!B3<>"",Transações!B3,"") -> Compra | D3: =IF(Transações!D3<>"",Transações!D3,"") -> 0.05 | E3: =IF(Transações!E3<>"",Transações!E3,"") -> 580000 | F3: =IF(C3="Compra",D3*E3,IF(C3="Staking",D3*E3,"")) -> 29000 | G3: =IF(C3="Venda",IF(COUNTIF(A$3:A2,A3)>0,(E3-SUMPRODUCT((A$3:A2=A3)*(C$3:C2="Compra")*F$3:F2)/IF(SUMPRODUCT((A$3:A2=A3)*(C$3:C2="Compra")*D$3:D2)=0,1,SUMPRODUCT((A$3:A2=A3)*(C$3:C2="Compra")*D$3:D2)))*D3,0),"") | H3: =IF(C3="Venda",E3*D3,"")
A4: =IF(Transações!C4<>"",Transações!C4,"") -> BTC | B4: =IF(Transações!A4<>"",Transações!A4,"") -> 20/01/2026 | C4: =IF(Transações!B4<>"",Transações!B4,"") -> Venda | D4: =IF(Transações!D4<>"",Transações!D4,"") -> 0.02 | E4: =IF(Transações!E4<>"",Transações!E4,"") -> 620000 | F4: =IF(C4="Compra",D4*E4,IF(C4="Staking",D4*E4,"")) | G4: =IF(C4="Venda",IF(COUNTIF(A$3:A3,A4)>0,(E4-SUMPRODUCT((A$3:A3=A4)*(C$3:C3="Compra")*F$3:F3)/IF(SUMPRODUCT((A$3:A3=A4)*(C$3:C3="Compra")*D$3:D3)=0,1,SUMPRODUCT((A$3:A3=A4)*(C$3:C3="Compra")*D$3:D3)))*D4,0),"") -> 800 | H4: =IF(C4="Venda",E4*D4,"") -> 12400
A5: =IF(Transações!C5<>"",Transações!C5,"") -> ETH | B5: =IF(Transações!A5<>"",Transações!A5,"") -> 05/02/2026 | C5: =IF(Transações!B5<>"",Transações!B5,"") -> Staking | D5: =IF(Transações!D5<>"",Transações!D5,"") -> 0.15 | E5: =IF(Transações!E5<>"",Transações!E5,"") -> 17500 | F5: =IF(C5="Compra",D5*E5,IF(C5="Staking",D5*E5,"")) -> 2625 | G5: =IF(C5="Venda",IF(COUNTIF(A$3:A4,A5)>0,(E5-SUMPRODUCT((A$3:A4=A5)*(C$3:C4="Compra")*F$3:F4)/IF(SUMPRODUCT((A$3:A4=A5)*(C$3:C4="Compra")*D$3:D4)=0,1,SUMPRODUCT((A$3:A4=A5)*(C$3:C4="Compra")*D$3:D4)))*D5,0),"") | H5: =IF(C5="Venda",E5*D5,"")
A6: =IF(Transações!C6<>"",Transações!C6,"") -> SOL | B6: =IF(Transações!A6<>"",Transações!A6,"") -> 18/02/2026 | C6: =IF(Transações!B6<>"",Transações!B6,"") -> Compra | D6: =IF(Transações!D6<>"",Transações!D6,"") -> 10 | E6: =IF(Transações!E6<>"",Transações!E6,"") -> 870 | F6: =IF(C6="Compra",D6*E6,IF(C6="Staking",D6*E6,"")) -> 8700 | G6: =IF(C6="Venda",IF(COUNTIF(A$3:A5,A6)>0,(E6-SUMPRODUCT((A$3:A5=A6)*(C$3:C5="Compra")*F$3:F5)/IF(SUMPRODUCT((A$3:A5=A6)*(C$3:C5="Compra")*D$3:D5)=0,1,SUMPRODUCT((A$3:A5=A6)*(C$3:C5="Compra")*D$3:D5)))*D6,0),"") | H6: =IF(C6="Venda",E6*D6,"")
A7: =IF(Transações!C7<>"",Transações!C7,"") | B7: =IF(Transações!A7<>"",Transações!A7,"") | C7: =IF(Transações!B7<>"",Transações!B7,"") | D7: =IF(Transações!D7<>"",Transações!D7,"") | E7: =IF(Transações!E7<>"",Transações!E7,"") | F7: =IF(C7="Compra",D7*E7,IF(C7="Staking",D7*E7,"")) | G7: =IF(C7="Venda",IF(COUNTIF(A$3:A6,A7)>0,(E7-SUMPRODUCT((A$3:A6=A7)*(C$3:C6="Compra")*F$3:F6)/IF(SUMPRODUCT((A$3:A6=A7)*(C$3:C6="Compra")*D$3:D6)=0,1,SUMPRODUCT((A$3:A6=A7)*(C$3:C6="Compra")*D$3:D6)))*D7,0),"") | H7: =IF(C7="Venda",E7*D7,"")
A8: =IF(Transações!C8<>"",Transações!C8,"") | B8: =IF(Transações!A8<>"",Transações!A8,"") | C8: =IF(Transações!B8<>"",Transações!B8,"") | D8: =IF(Transações!D8<>"",Transações!D8,"") | E8: =IF(Transações!E8<>"",Transações!E8,"") | F8: =IF(C8="Compra",D8*E8,IF(C8="Staking",D8*E8,"")) | G8: =IF(C8="Venda",IF(COUNTIF(A$3:A7,A8)>0,(E8-SUMPRODUCT((A$3:A7=A8)*(C$3:C7="Compra")*F$3:F7)/IF(SUMPRODUCT((A$3:A7=A8)*(C$3:C7="Compra")*D$3:D7)=0,1,SUMPRODUCT((A$3:A7=A8)*(C$3:C7="Compra")*D$3:D7)))*D8,0),"") | H8: =IF(C8="Venda",E8*D8,"")
A9: =IF(Transações!C9<>"",Transações!C9,"") | B9: =IF(Transações!A9<>"",Transações!A9,"") | C9: =IF(Transações!B9<>"",Transações!B9,"") | D9: =IF(Transações!D9<>"",Transações!D9,"") | E9: =IF(Transações!E9<>"",Transações!E9,"") | F9: =IF(C9="Compra",D9*E9,IF(C9="Staking",D9*E9,"")) | G9: =IF(C9="Venda",IF(COUNTIF(A$3:A8,A9)>0,(E9-SUMPRODUCT((A$3:A8=A9)*(C$3:C8="Compra")*F$3:F8)/IF(SUMPRODUCT((A$3:A8=A9)*(C$3:C8="Compra")*D$3:D8)=0,1,SUMPRODUCT((A$3:A8=A9)*(C$3:C8="Compra")*D$3:D8)))*D9,0),"") | H9: =IF(C9="Venda",E9*D9,"")
A10: =IF(Transações!C10<>"",Transações!C10,"") | B10: =IF(Transações!A10<>"",Transações!A10,"") | C10: =IF(Transações!B10<>"",Transações!B10,"") | D10: =IF(Transações!D10<>"",Transações!D10,"") | E10: =IF(Transações!E10<>"",Transações!E10,"") | F10: =IF(C10="Compra",D10*E10,IF(C10="Staking",D10*E10,"")) | G10: =IF(C10="Venda",IF(COUNTIF(A$3:A9,A10)>0,(E10-SUMPRODUCT((A$3:A9=A10)*(C$3:C9="Compra")*F$3:F9)/IF(SUMPRODUCT((A$3:A9=A10)*(C$3:C9="Compra")*D$3:D9)=0,1,SUMPRODUCT((A$3:A9=A10)*(C$3:C9="Compra")*D$3:D9)))*D10,0),"") | H10: =IF(C10="Venda",E10*D10,"")
A11: =IF(Transações!C11<>"",Transações!C11,"") | B11: =IF(Transações!A11<>"",Transações!A11,"") | C11: =IF(Transações!B11<>"",Transações!B11,"") | D11: =IF(Transações!D11<>"",Transações!D11,"") | E11: =IF(Transações!E11<>"",Transações!E11,"") | F11: =IF(C11="Compra",D11*E11,IF(C11="Staking",D11*E11,"")) | G11: =IF(C11="Venda",IF(COUNTIF(A$3:A10,A11)>0,(E11-SUMPRODUCT((A$3:A10=A11)*(C$3:C10="Compra")*F$3:F10)/IF(SUMPRODUCT((A$3:A10=A11)*(C$3:C10="Compra")*D$3:D10)=0,1,SUMPRODUCT((A$3:A10=A11)*(C$3:C10="Compra")*D$3:D10)))*D11,0),"") | H11: =IF(C11="Venda",E11*D11,"")
A12: =IF(Transações!C12<>"",Transações!C12,"") | B12: =IF(Transações!A12<>"",Transações!A12,"") | C12: =IF(Transações!B12<>"",Transações!B12,"") | D12: =IF(Transações!D12<>"",Transações!D12,"") | E12: =IF(Transações!E12<>"",Transações!E12,"") | F12: =IF(C12="Compra",D12*E12,IF(C12="Staking",D12*E12,"")) | G12: =IF(C12="Venda",IF(COUNTIF(A$3:A11,A12)>0,(E12-SUMPRODUCT((A$3:A11=A12)*(C$3:C11="Compra")*F$3:F11)/IF(SUMPRODUCT((A$3:A11=A12)*(C$3:C11="Compra")*D$3:D11)=0,1,SUMPRODUCT((A$3:A11=A12)*(C$3:C11="Compra")*D$3:D11)))*D12,0),"") | H12: =IF(C12="Venda",E12*D12,"")
A13: =IF(Transações!C13<>"",Transações!C13,"") | B13: =IF(Transações!A13<>"",Transações!A13,"") | C13: =IF(Transações!B13<>"",Transações!B13,"") | D13: =IF(Transações!D13<>"",Transações!D13,"") | E13: =IF(Transações!E13<>"",Transações!E13,"") | F13: =IF(C13="Compra",D13*E13,IF(C13="Staking",D13*E13,"")) | G13: =IF(C13="Venda",IF(COUNTIF(A$3:A12,A13)>0,(E13-SUMPRODUCT((A$3:A12=A13)*(C$3:C12="Compra")*F$3:F12)/IF(SUMPRODUCT((A$3:A12=A13)*(C$3:C12="Compra")*D$3:D12)=0,1,SUMPRODUCT((A$3:A12=A13)*(C$3:C12="Compra")*D$3:D12)))*D13,0),"") | H13: =IF(C13="Venda",E13*D13,"")
A14: =IF(Transações!C14<>"",Transações!C14,"") | B14: =IF(Transações!A14<>"",Transações!A14,"") | C14: =IF(Transações!B14<>"",Transações!B14,"") | D14: =IF(Transações!D14<>"",Transações!D14,"") | E14: =IF(Transações!E14<>"",Transações!E14,"") | F14: =IF(C14="Compra",D14*E14,IF(C14="Staking",D14*E14,"")) | G14: =IF(C14="Venda",IF(COUNTIF(A$3:A13,A14)>0,(E14-SUMPRODUCT((A$3:A13=A14)*(C$3:C13="Compra")*F$3:F13)/IF(SUMPRODUCT((A$3:A13=A14)*(C$3:C13="Compra")*D$3:D13)=0,1,SUMPRODUCT((A$3:A13=A14)*(C$3:C13="Compra")*D$3:D13)))*D14,0),"") | H14: =IF(C14="Venda",E14*D14,"")
... A1002: =IF(Transações!C1002<>"",Transações!C1002,"") | B1002: =IF(Transações!A1002<>"",Transações!A1002,"") | C1002: =IF(Transações!B1002<>"",Transações!B1002,"") | D1002: =IF(Transações!D1002<>"",Transações!D1002,"") | E1002: =IF(Transações!E1002<>"",Transações!E1002,"") | F1002: =IF(C1002="Compra",D1002*E1002,IF(C1002="Staking",D1002*E1002,"")) | G1002: =IF(C1002="Venda",IF(COUNTIF(A$3:A1001,A1002)>0,(E1002-SUMPRODUCT((A$3:A1001=A1002)*(C$3:C1001="Compra")*F$3:F1001)/IF(SUMPRODUCT((A$3:A1001=A1002)*(C$3:C1001="Compra")*D$3:D1001)=0,1,SUMPRODUCT((A$3:A1001=A1002)*(C$3:C1001="Compra")*D$3:D1001)))*D1002,0),"") | H1002: =IF(C1002="Venda",E1002*D1002,"")

Sheet Resumo e DARF
A1: 🇧🇷 RESUMO MENSAL E GUIA DARF – IR CRIPTOATIVOS 2026
A2: 📅 PERÍODO DE APURAÇÃO (MÊS ATUAL)
A3: Mês/Ano de Referência | B3: =TEXT(TODAY(),"MM/YYYY") -> 03/2026 | C3: Atualiza automaticamente
A4: Primeiro dia do mês | B4: =DATE(YEAR(TODAY()),MONTH(TODAY()),1) -> 46082
A5: Último dia do mês | B5: =EOMONTH(TODAY(),0) -> 46112
A7: 💰 APURAÇÃO DE VENDAS NO MÊS
A8: Total de Vendas no Mês (BRL) | B8: =IFERROR(SUMIF(Transações!B3:B1002,"Venda",Transações!F3:F1002),0) -> 12400 | C8: Todas as vendas do mês
A9: Total Ganho de Capital (BRL) | B9: =IFERROR(SUM('Apuração FIFO'!G3:G1002),0) -> 800 | C9: Soma dos ganhos apurados
A10: Limite de Isenção Mensal | B10: =35000 -> 35000 | C10: R$ 35.000 – Instrução 2026
A11: Vendas acima do limite? | B11: =IF(B8>B10,"⚠️ SIM – DARF OBRIGATÓRIO","✅ NÃO – Isento") -> ✅ NÃO – Isento
A13: 🧮 CÁLCULO DO IMPOSTO
A14: Base de Cálculo (Ganho Tributável) | B14: =MAX(B9,0) -> 800 | C14: Ganho positivo
A15: Alíquota IR | B15: =0.15 -> 0.15 | C15: 15% – ganho até R$5mi
A16: Imposto Devido (BRL) | B16: =IF(B8>B10,B14*B15,0) -> 0 | C16: Zero se vendas ≤ 35k
A17: Multa por Atraso (0,33%/dia) | B17: =B16*0.0033 -> 0 | C17: Se pagar após vencimento
A18: Juros SELIC (estimativa 1%/mês) | B18: =B16*0.01 -> 0 | C18: Consulte SELIC vigente
A20: 📋 INFORMAÇÕES DARF
A21: Código DARF | B21: 4600 | C21: Ganhos em renda variável
A22: Competência | B22: =TEXT(TODAY(),"MM/YYYY") -> 03/2026 | C22: Mês de apuração
A23: Vencimento DARF | B23: =TEXT(EOMONTH(TODAY(),0)+1,"DD/MM/YYYY") -> 01/04/2026 | C23: Último dia útil mês seguinte
A24: CPF/CNPJ | B24: Preencha aqui | C24: Seu CPF ou CNPJ
A25: Valor a Pagar | B25: =B16 -> 0 | C25: Imposto devido (= campo B16)
A27: 📊 RESUMO POR CRIPTOATIVO
A28: Use tabela dinâmica ou Apuração FIFO para detalhes por ativo

Sheet Instruções
A1: 📘 GUIA COMPLETO – CALCULADORA IR CRIPTOATIVOS BRASIL 2026
A3: 🟢 COMO USAR ESTA PLANILHA
A5: ▪ 1. ABA «Transações»: Preencha cada operação com cripto: Data (DD/MM/AAAA), Tipo (Compra | Venda | Staking | Swap | Transferência), Cripto (BTC, ETH, SOL…), Quantidade, Preço Unitário em BRL e Taxas pagas. A coluna «Valor Total» é calculada automaticamente pela fórmula =Quantidade × Preço Unitário.
A6: ▪ 2. ABA «Apuração FIFO»: Os dados são puxados automaticamente da aba Transações. A coluna «Ganho de Capital» usa o método Custo Médio Ponderado (CMP) aceito pela Receita Federal: para cada venda, o custo médio é calculado sobre todas as compras anteriores do mesmo ativo. Esse método é equivalente ao FIFO para fins práticos de apuração mensal conforme IN RFB 1.888/2019 e atualizações 2026.
A7: ▪ 3. ABA «Resumo e DARF»: Resumo automático do mês atual usando HOJE(). Mostra vendas totais, ganho de capital, imposto devido (15%) e informações do DARF (código 4600). Atualize manualmente o CPF/CNPJ.
A8: ▪ 4. ABA «Instruções»: Este guia com regras vigentes e orientações de uso.
A10: 📜 REGRAS DA RECEITA FEDERAL – 2026
A12: ▪ Isenção de R$ 35.000/mês: Pessoas físicas estão isentas de IR sobre ganho de capital em alienações de criptoativos cujo total de vendas no mês não ultrapasse R$ 35.000 (trinta e cinco mil reais). Acima desse valor, todo o ganho é tributável. Base legal: Lei 14.754/2023 e regulamentações posteriores.
A13: ▪ Alíquotas progressivas (art. 21 Lei 8.981/95): • Ganho até R$ 5.000.000 → 15% • Ganho de R$ 5.000.001 a R$ 10.000.000 → 17,5% • Ganho de R$ 10.000.001 a R$ 20.000.000 → 20% • Ganho acima de R$ 20.000.000 → 22,5% (Esta planilha usa 15% como padrão – ajuste na célula B15 da aba Resumo se necessário.)
A14: ▪ Método de Custo (CMP): A Receita Federal aceita o Custo Médio Ponderado para apuração de ganho de capital. O custo de aquisição deve incluir corretagens e taxas pagas na compra.
A15: ▪ Prazo de pagamento do DARF: O DARF (código 4600) deve ser pago até o último dia útil do mês seguinte ao da alienação. Pagamentos em atraso sofrem multa de 0,33% ao dia (máx. 20%) + juros SELIC.
A16: ▪ Staking e Rendimentos DeFi: Rendimentos de staking, yield farming e DeFi são tributados como rendimentos de capital (Carnê-Leão ou IRPF), e não como ganho de capital. Declare na ficha «Rendimentos Tributáveis Recebidos de PJ» ou Carnê-Leão mensal se o pagador não fizer retenção. A Instrução Normativa RFB 2.180/2024 equipara exchanges nacionais a corretoras para fins de retenção.
... A34: ▪ Carnê-Leão Web: https://carne-leao.esocial.gov.br/
